semgrep_mcp/__init__.py
semgrep_mcp/__main__.py
semgrep_mcp/models.py
semgrep_mcp/semgrep.py
semgrep_mcp/server.py
semgrep_mcp/version.py
semgrep_mcp/semgrep_interfaces/.codemapignore
semgrep_mcp/semgrep_interfaces/.git
semgrep_mcp/semgrep_interfaces/.gitattributes
semgrep_mcp/semgrep_interfaces/.gitignore
semgrep_mcp/semgrep_interfaces/LICENSE
semgrep_mcp/semgrep_interfaces/Language.ml
semgrep_mcp/semgrep_interfaces/Language.mli
semgrep_mcp/semgrep_interfaces/Makefile
semgrep_mcp/semgrep_interfaces/NOTICE
semgrep_mcp/semgrep_interfaces/README.md
semgrep_mcp/semgrep_interfaces/__init__.py
semgrep_mcp/semgrep_interfaces/generate
semgrep_mcp/semgrep_interfaces/generate.py
semgrep_mcp/semgrep_interfaces/lang.json
semgrep_mcp/semgrep_interfaces/rule_schema_v1.yaml
semgrep_mcp/semgrep_interfaces/rule_schema_v2.atd
semgrep_mcp/semgrep_interfaces/rule_schema_v2_adapter.ml
semgrep_mcp/semgrep_interfaces/semgrep-interfaces.opam
semgrep_mcp/semgrep_interfaces/semgrep_metrics.atd
semgrep_mcp/semgrep_interfaces/semgrep_metrics.py
semgrep_mcp/semgrep_interfaces/semgrep_output_v1.atd
semgrep_mcp/semgrep_interfaces/semgrep_output_v1.jsonschema
semgrep_mcp/semgrep_interfaces/semgrep_output_v1.proto
semgrep_mcp/semgrep_interfaces/semgrep_output_v1.py
semgrep_mcp/semgrep_interfaces/semgrep_output_v1.ts
semgrep_mcp/semgrep_interfaces/semgrep_output_v1_j.ml
semgrep_mcp/semgrep_interfaces/semgrep_output_v1_j.mli
semgrep_mcp/semgrep_interfaces/semgrep_runner_v1.proto
semgrep_mcp/semgrep_interfaces/semgrep_studio_v1.proto
semgrep_mcp/semgrep_interfaces/.github/pull_request_template.md
semgrep_mcp/semgrep_interfaces/.github/workflows/lint.yaml
semgrep_mcp/semgrep_interfaces/scripts/check-backwards-compatibility
semgrep_mcp/semgrep_interfaces/scripts/jsonschema2protobuf.py
semgrep_mcp/semgrep_interfaces/tests/.gitignore
semgrep_mcp/semgrep_interfaces/tests/Makefile
semgrep_mcp/semgrep_interfaces/tests/jsonschema/Makefile
semgrep_mcp/semgrep_interfaces/tests/jsonschema/validate
semgrep_mcp-0.9.0.dist-info/METADATA
semgrep_mcp-0.9.0.dist-info/WHEEL
semgrep_mcp-0.9.0.dist-info/entry_points.txt
semgrep_mcp-0.9.0.dist-info/licenses/LICENSE
semgrep_mcp-0.9.0.dist-info/RECORD
