Metadata-Version: 2.4
Name: semgrep-mcp
Version: 0.9.0
Summary: MCP Server for using Semgrep to scan code
Project-URL: Homepage, https://github.com/semgrep/mcp
Project-URL: Repository, https://github.com/semgrep/mcp.git
Project-URL: Issues, https://github.com/semgrep/mcp/issues
Project-URL: Documentation, https://github.com/semgrep/mcp#readme
Project-URL: Changelog, https://github.com/semgrep/mcp/blob/main/CHANGELOG.md
Author-email: "Semgrep, Inc." <hello@semgrep.com>, Seth Jaksik <seth@semgrep.com>, Drew Dennison <drew@semgrep.com>
License: MIT
License-File: LICENSE
Keywords: code-scanning,mcp,security,semgrep,static-analysis
Classifier: Development Status :: 4 - Beta
Classifier: Intended Audience :: Developers
Classifier: License :: OSI Approved :: MIT License
Classifier: Programming Language :: Python :: 3
Classifier: Programming Language :: Python :: 3.10
Classifier: Programming Language :: Python :: 3.11
Classifier: Programming Language :: Python :: 3.12
Classifier: Programming Language :: Python :: 3.13
Classifier: Topic :: Security
Classifier: Topic :: Software Development :: Quality Assurance
Requires-Python: >=3.10
Requires-Dist: mcp==1.12.2
Requires-Dist: opentelemetry-api>=1.25.0
Requires-Dist: opentelemetry-sdk>=1.25.0
Requires-Dist: semgrep==1.135.0
